GusPI/__init__.py
GusPI/cal.py
GusPI/finPy (1).py
GusPI/finPy.py
GusPI/helper.py
GusPI/scraper.py
GusPI/statsPy.py
GusPI/suPy.py
GusPI-0.0.59.dist-info/LICENSE
GusPI-0.0.59.dist-info/METADATA
GusPI-0.0.59.dist-info/WHEEL
GusPI-0.0.59.dist-info/top_level.txt
GusPI-0.0.59.dist-info/RECORD
