Metadata-Version: 2.1
Name: GusPI
Version: 0.0.59
Summary: This open-source python package aims to provide statistical support in supply chain analytics and finance/accounting analytics. We welcome everyone to use this python package for personal or professional projects. Please let us know any feedback you have. We'd love to improve the package and add feature enhancements to benefit researchers.
Home-page: https://github.com/ygeszvain/GusPI
Author: Randy Geszvain
Author-email: randy.geszvain@gmail.com
License: UNKNOWN
Keywords: finance,supply chain,analytics
Platform: UNKNOWN
Classifier: Programming Language :: Python :: 3
Classifier: License :: OSI Approved :: MIT License
Classifier: Operating System :: OS Independent
Requires-Dist: pandas
Requires-Dist: matplotlib
Requires-Dist: seaborn
Requires-Dist: plotly
Requires-Dist: numpy
Requires-Dist: beautifulsoup4
Requires-Dist: simfin
Requires-Dist: scipy
